fastapi_user_auth/__init__.py
fastapi_user_auth/admin/__init__.py
fastapi_user_auth/admin/actions.py
fastapi_user_auth/admin/admin.py
fastapi_user_auth/admin/app.py
fastapi_user_auth/admin/site.py
fastapi_user_auth/admin/utils.py
fastapi_user_auth/auth/__init__.py
fastapi_user_auth/auth/auth.py
fastapi_user_auth/auth/exceptions.py
fastapi_user_auth/auth/model.conf
fastapi_user_auth/auth/models.py
fastapi_user_auth/auth/schemas.py
fastapi_user_auth/auth/backends/__init__.py
fastapi_user_auth/auth/backends/base.py
fastapi_user_auth/auth/backends/db.py
fastapi_user_auth/auth/backends/jwt.py
fastapi_user_auth/auth/backends/redis.py
fastapi_user_auth/globals/__init__.py
fastapi_user_auth/globals/deps.py
fastapi_user_auth/locale/zh_CN/LC_MESSAGES/messages.mo
fastapi_user_auth/locale/zh_CN/LC_MESSAGES/messages.po
fastapi_user_auth/mixins/__init__.py
fastapi_user_auth/mixins/admin.py
fastapi_user_auth/mixins/models.py
fastapi_user_auth/utils/__init__.py
fastapi_user_auth/utils/casbin.py
fastapi_user_auth/utils/sqlachemy_adapter.py
fastapi_user_auth/utils/sqltypes.py
fastapi_user_auth-0.7.3.dist-info/WHEEL
fastapi_user_auth-0.7.3.dist-info/METADATA
fastapi_user_auth-0.7.3.dist-info/RECORD
