Metadata-Version: 2.1
Name: fastapi_user_auth
Version: 0.7.3
Summary: FastAPI-User-Auth is a simple and powerful FastAPI user RBAC authentication and authorization library. Based on FastAPI-Amis-Admin and provides a freely extensible visual management interface.
Keywords: fastapi,fastapi-user-auth,fastapi-amis-admin,fastapi-auth,fastapi-users,fastapi-jwt-auth,sqlmodel
Author-email: Atomi <1456417373@qq.com>
Maintainer-email: Atomi <1456417373@qq.com>
Requires-Python: >=3.8
Classifier: Framework :: FastAPI
Classifier: Environment :: Web Environment
Classifier: Topic :: System :: Systems Administration
Classifier: License :: OSI Approved :: Apache Software License
Classifier: Operating System :: OS Independent
Classifier: Programming Language :: Python :: 3
Classifier: Programming Language :: Python :: 3.8
Classifier: Programming Language :: Python :: 3.9
Classifier: Programming Language :: Python :: 3.10
Classifier: Programming Language :: Python :: 3.11
Requires-Dist: fastapi-amis-admin>=0.7.1,<0.8.0
Requires-Dist: email-validator>=1.3.1,<3.0.0
Requires-Dist: passlib>=1.7.4
Requires-Dist: bcrypt>=4.0.0,<4.1.0
Requires-Dist: casbin>=1.34.0
Requires-Dist: python-jose>=3.3.0 ; extra == "jwt"
Requires-Dist: redis>=4.2.0 ; extra == "redis"
Requires-Dist: uvicorn[standard] >=0.19.0,<1.0 ; extra == "test"
Requires-Dist: pytest >=6.2.4 ; extra == "test"
Requires-Dist: pytest-asyncio>=0.17,<0.23.0 ; extra == "test"
Requires-Dist: aiosqlite>=0.15.0 ; extra == "test"
Requires-Dist: python-jose>=3.3.0 ; extra == "test"
Requires-Dist: jinja2 >=2.11.2,<4.0.0 ; extra == "test"
Requires-Dist: ujson>=5.5.0 ; extra == "test"
Requires-Dist: requests>=2.28.1 ; extra == "test"
Requires-Dist: pre-commit>=2.20.0 ; extra == "test"
Requires-Dist: httpx>=0.23.3 ; extra == "test"
Requires-Dist: pydantic-settings>=2.0.0 ; extra == "test"
Requires-Dist: sqlmodelx>=0.0.11 ; extra == "test"
Project-URL: Documentation, http://docs.amis.work/
Project-URL: FastAPI-Amis-Admin, https://github.com/amisadmin/fastapi_amis_admin
Project-URL: Source, https://github.com/amisadmin/fastapi_user_auth
Provides-Extra: jwt
Provides-Extra: redis
Provides-Extra: test
